{
  "header": {
    "cycle_id": 52,
    "mode": "CVT",
    "num_slots": 4,
    "sensor_ids": [
      1,
      2,
      3,
      4,
      5,
      6,
      7,
      8,
      9,
      10,
      11,
      12
    ],
    "num_frames_averaged": 5,
    "merged_all_index": 52
  },
  "pc_timestamp": 1779612866.5222902,
  "slot_data": [
    {
      "slot": 0,
      "sensor_data": [
        {
          "id": 1,
          "x": 0.06806433349847793,
          "y": -8.11075668334961,
          "z": 0.8096910834312439
        },
        {
          "id": 2,
          "x": 0.05906655415892601,
          "y": -8.144917106628418,
          "z": 0.7772894024848938
        },
        {
          "id": 3,
          "x": 0.06078122407197952,
          "y": -8.165584564208984,
          "z": 0.737956428527832
        },
        {
          "id": 4,
          "x": 0.08142186105251312,
          "y": -8.305010986328124,
          "z": 0.8639646649360657
        },
        {
          "id": 5,
          "x": 0.08079806864261627,
          "y": -8.310937881469727,
          "z": 0.8155487298965454
        },
        {
          "id": 6,
          "x": 0.08653143048286438,
          "y": -8.420503997802735,
          "z": 0.7839175224304199
        },
        {
          "id": 7,
          "x": -0.037483391165733335,
          "y": -8.07687816619873,
          "z": 0.81058748960495
        },
        {
          "id": 8,
          "x": -0.023707693442702293,
          "y": -8.115128326416016,
          "z": 0.7639907956123352
        },
        {
          "id": 9,
          "x": -0.037156886607408526,
          "y": -8.14980182647705,
          "z": 0.7214679718017578
        },
        {
          "id": 10,
          "x": -0.053946254402399064,
          "y": -8.28917999267578,
          "z": 0.8629870057106018
        },
        {
          "id": 11,
          "x": -0.05605407804250717,
          "y": -8.336337471008301,
          "z": 0.8243482232093811
        },
        {
          "id": 12,
          "x": -0.04791268035769462,
          "y": -8.355742263793946,
          "z": 0.7795278310775757
        }
      ],
      "pose": {
        "position": {
          "x": 0.01433068896040638,
          "y": -0.07979106076667379,
          "z": 0.1658318375319697
        },
        "rotation": {
          "x": 0.8798213238030103,
          "y": 0.025212581932966376,
          "z": 0.059464687143169506,
          "w": -0.4708956517921536
        }
      }
    },
    {
      "slot": 1,
      "sensor_data": [
        {
          "id": 1,
          "x": 13.692645454406739,
          "y": 1.4667901039123534,
          "z": 3.816153383255005
        },
        {
          "id": 2,
          "x": 13.792833137512208,
          "y": 1.4603041887283326,
          "z": 3.7389595031738283
        },
        {
          "id": 3,
          "x": 13.869804382324219,
          "y": 1.4952263832092285,
          "z": 3.6550852775573732
        },
        {
          "id": 4,
          "x": 13.599783515930175,
          "y": 1.6644943714141847,
          "z": 3.811635160446167
        },
        {
          "id": 5,
          "x": 13.636818504333496,
          "y": 1.6648419380187989,
          "z": 3.7116072177886963
        },
        {
          "id": 6,
          "x": 13.844527626037598,
          "y": 1.6999237537384033,
          "z": 3.6812424182891847
        },
        {
          "id": 7,
          "x": 14.093596649169921,
          "y": 1.7003446340560913,
          "z": 4.0717696189880375
        },
        {
          "id": 8,
          "x": 14.219941329956054,
          "y": 1.7317004919052124,
          "z": 4.002831268310547
        },
        {
          "id": 9,
          "x": 14.285115242004395,
          "y": 1.7302334547042846,
          "z": 3.906797695159912
        },
        {
          "id": 10,
          "x": 13.932385635375976,
          "y": 1.8599170207977296,
          "z": 4.08898286819458
        },
        {
          "id": 11,
          "x": 14.100493240356446,
          "y": 1.891110396385193,
          "z": 4.008340167999267
        },
        {
          "id": 12,
          "x": 14.20256519317627,
          "y": 1.9242563724517823,
          "z": 3.929870128631592
        }
      ],
      "pose": {
        "position": {
          "x": 0.1726396503008508,
          "y": 0.3097546807938022,
          "z": 0.19361944661144737
        },
        "rotation": {
          "x": 0.1509321824493883,
          "y": 0.8894467709268086,
          "z": -0.3711752626356337,
          "w": -0.2198473160998471
        }
      }
    },
    {
      "slot": 2,
      "sensor_data": [
        {
          "id": 1,
          "x": -8.707726287841798,
          "y": 3.450891399383545,
          "z": 1.8049633264541627
        },
        {
          "id": 2,
          "x": -8.77976303100586,
          "y": 3.4705684185028076,
          "z": 1.740075707435608
        },
        {
          "id": 3,
          "x": -8.85001335144043,
          "y": 3.5034313201904297,
          "z": 1.6774374485015868
        },
        {
          "id": 4,
          "x": -8.55812473297119,
          "y": 3.541188144683838,
          "z": 1.7076964855194092
        },
        {
          "id": 5,
          "x": -8.599229621887208,
          "y": 3.5548133850097656,
          "z": 1.6124904870986938
        },
        {
          "id": 6,
          "x": -8.750993537902833,
          "y": 3.6181812286376953,
          "z": 1.5515896797180175
        },
        {
          "id": 7,
          "x": -8.459047889709472,
          "y": 3.2727622509002687,
          "z": 1.6617263317108155
        },
        {
          "id": 8,
          "x": -8.52548770904541,
          "y": 3.310779905319214,
          "z": 1.5834214210510253
        },
        {
          "id": 9,
          "x": -8.60394115447998,
          "y": 3.319485378265381,
          "z": 1.5020097732543944
        },
        {
          "id": 10,
          "x": -8.314478492736816,
          "y": 3.362827253341675,
          "z": 1.5450751781463623
        },
        {
          "id": 11,
          "x": -8.39657382965088,
          "y": 3.402959442138672,
          "z": 1.4961493492126465
        },
        {
          "id": 12,
          "x": -8.452314567565917,
          "y": 3.436308479309082,
          "z": 1.4307196378707885
        }
      ],
      "pose": {
        "position": {
          "x": -0.17931949523910767,
          "y": 0.2848391165869418,
          "z": 0.1793626969774629
        },
        "rotation": {
          "x": -0.2145487719040602,
          "y": 0.8912790080424657,
          "z": -0.32272542760196166,
          "w": 0.23545456605559514
        }
      }
    },
    {
      "slot": 3,
      "sensor_data": [
        {
          "id": 1,
          "x": 0.014334816858172417,
          "y": -0.18855878114700317,
          "z": -0.42889236807823183
        },
        {
          "id": 2,
          "x": 0.013859663158655167,
          "y": -0.19319091141223907,
          "z": -0.4245545446872711
        },
        {
          "id": 3,
          "x": 0.008378963451832533,
          "y": -0.18905794024467468,
          "z": -0.4201943755149841
        },
        {
          "id": 4,
          "x": 0.020589405298233034,
          "y": -0.19287653267383575,
          "z": -0.4266670703887939
        },
        {
          "id": 5,
          "x": 0.016372283175587653,
          "y": -0.18671826422214508,
          "z": -0.4270415961742401
        },
        {
          "id": 6,
          "x": 0.016532160714268683,
          "y": -0.19465475976467134,
          "z": -0.4315238356590271
        },
        {
          "id": 7,
          "x": 0.02110992819070816,
          "y": -0.1887048989534378,
          "z": -0.42172411680221555
        },
        {
          "id": 8,
          "x": 0.027719793468713762,
          "y": -0.18328453004360198,
          "z": -0.4230445921421051
        },
        {
          "id": 9,
          "x": 0.01941840760409832,
          "y": -0.193192657828331,
          "z": -0.4262269973754883
        },
        {
          "id": 10,
          "x": 0.026180852204561234,
          "y": -0.19544266164302826,
          "z": -0.43117796778678896
        },
        {
          "id": 11,
          "x": 0.020615139976143837,
          "y": -0.19290794432163239,
          "z": -0.43272035717964175
        },
        {
          "id": 12,
          "x": 0.024019965529441835,
          "y": -0.18963575065135957,
          "z": -0.4378360748291016
        }
      ],
      "pose": null
    }
  ],
  "ground_truth_pose": {
    "position": {
      "x": 0.004104510856757518,
      "y": 0.20093399184525232,
      "z": 0.07966258789963415
    },
    "rotation": {
      "x": -0.005425348753761575,
      "y": 0.005508041374311498,
      "z": 0.08121770078729443,
      "w": 0.9966663996292563
    }
  },
  "localization": {
    "pose": {
      "position": {
        "x": 0.006877645122713869,
        "y": 0.2108981714038343,
        "z": 0.1065575684753813
      },
      "orientation": {
        "x": 0.017325589905389058,
        "y": -0.033513530569512555,
        "z": 0.04838104181576295,
        "w": 0.9981161966404603
      }
    },
    "position_error": 0.02881518919081567,
    "orientation_error": 0.11173984498660668
  },
  "localization_cci": {
    "pose": {
      "position": {
        "x": 0.006112117506962251,
        "y": 0.21385302352434937,
        "z": 0.09981765924118961
      },
      "orientation": {
        "x": 0.03436474547848471,
        "y": -0.03648327381604247,
        "z": 0.04971938060597636,
        "w": 0.9975048963248355
      }
    },
    "position_error": 0.024024128803572666,
    "orientation_error": 0.13177161283289698
  },
  "localization_sensors_1346791012": {
    "pose": {
      "position": {
        "x": 0.0052249067671017125,
        "y": 0.20914956716692507,
        "z": 0.10468158688881996
      },
      "orientation": {
        "x": 0.011422398787894247,
        "y": -0.021203856225495962,
        "z": 0.05548267708179404,
        "w": 0.9981691228599171
      }
    },
    "position_error": 0.02635718640680136,
    "orientation_error": 0.08153899457722014
  },
  "localization_cci_sensors_1346791012": {
    "pose": {
      "position": {
        "x": 0.00289980435000113,
        "y": 0.21152995515115594,
        "z": 0.09731087373432447
      },
      "orientation": {
        "x": 0.02904953793386677,
        "y": -0.02251725592714845,
        "z": 0.05612081365350967,
        "w": 0.9977472384357714
      }
    },
    "position_error": 0.020620081208627867,
    "orientation_error": 0.10208864260476487
  },
  "combined_merge_source": {
    "source_result_dir": "result_8",
    "source_cycle_file": "cycle_0010.json",
    "source_cycle_id": 10
  },
  "localization_sensors_2312": {
    "pose": {
      "position": {
        "x": 0.010102874384881104,
        "y": 0.21631144427370286,
        "z": 0.11571395215058201
      },
      "orientation": {
        "x": -0.028512455220579477,
        "y": -0.06874944044818626,
        "z": 0.08117266433429629,
        "w": 0.9939172766886727
      }
    },
    "position_error": 0.03965031238917676,
    "orientation_error": 0.15566380777982206
  },
  "localization_cci_sensors_2312": {
    "pose": {
      "position": {
        "x": 0.001956659132568072,
        "y": 0.22409876460489223,
        "z": 0.10450355332440793
      },
      "orientation": {
        "x": -0.008813615427678334,
        "y": -0.08963997399494925,
        "z": 0.06971197728165497,
        "w": 0.9934924435891599
      }
    },
    "position_error": 0.0340337116293487,
    "orientation_error": 0.19198076705592387
  }
}
